MANIFEST.in
README
setup.py
Haus.egg-info/PKG-INFO
Haus.egg-info/SOURCES.txt
Haus.egg-info/dependency_links.txt
Haus.egg-info/entry_points.txt
Haus.egg-info/requires.txt
Haus.egg-info/top_level.txt
haus/__init__.py
haus/cli.py
haus/configspec.conf
haus/core.py
haus/components/__init__.py
haus/components/abstract.py
haus/components/appinit.py
haus/components/barrelsec.py
haus/components/beakerstate.py
haus/components/genshiview.py
haus/components/locations.py
haus/components/logger.py
haus/components/prefixer.py
haus/components/selectordispatch.py
haus/components/standard.py
haus/components/staticfiles.py
haus/components/status.py
haus/components/yaroreq.py
haus/html/denied.html
haus/html/login.html
haus/html/logout.html
haus/html/status404.html
haus/html/status405.html
haus/html/status500.html
haus/init/MANIFEST.in.tpl
haus/init/setup.py.tpl
haus/init/+package_name+/__init__.py.tpl
haus/init/+package_name+/app.conf.tpl
haus/init/+package_name+/demo.py.tpl
haus/init/+package_name+/urls.map.tpl
haus/init/+package_name+/html/welcome.html
haus/init/+package_name+/html/_layouts/default.html.tpl
haus/init/+package_name+/static/default.css