Metadata-Version: 1.0
Name: Haus
Version: 0.1.0
Summary: A loosely joined WSGI-centric Web programming framework.
Home-page: http://houseofhaus.org/
Author: Luke Arno
Author-email: luke.arno@gmail.com
License: LGPL
Keywords: wsgi web http framework rest
Platform: UNKNOWN
Classifier: Development Status :: 3 - Alpha
Classifier: Environment :: Web Environment
Classifier: Intended Audience :: Developers
Classifier: License :: OSI Approved :: GNU Library or Lesser General Public License (LGPL)
Classifier: Natural Language :: English
Classifier: Operating System :: OS Independent
Classifier: Programming Language :: Python
Classifier: Topic :: Software Development :: Libraries
Classifier: Topic :: Utilities
